bizyui/__init__.py
bizyui/js/__init__.py
bizyui/js/apis.js
bizyui/js/apply_image_to_node.js
bizyui/js/aspect_ratio.js
bizyui/js/bizyair_frontend.js
bizyui/js/bizyair_tools.js
bizyui/js/connection_color.js
bizyui/js/dataset_apply.js
bizyui/js/deprecated.js
bizyui/js/handle_load_nodes.js
bizyui/js/handle_node_configure.js
bizyui/js/image_caption.js
bizyui/js/image_upload.js
bizyui/js/limit_time_range.js
bizyui/js/menus.js
bizyui/js/model_apply.js
bizyui/js/model_price.js
bizyui/js/sam_loader.js
bizyui/js/share_load_controlnet.js
bizyui/js/share_lora_loader.js
bizyui/js/siliconcloud_llm_api.js
bizyui/js/third_party_vlm_api.js
bizyui/js/dialog/sam_edit.js
bizyui/js/subassembly/dialog.js
bizyui/js/subassembly/styleDialog.js
bizyui/js/subassembly/styleMenus.js
bizyui/js/subassembly/tools.js
bizyui/js/utils/dialog.js
bizyui/js/utils/el.js
bizyui-1.2.94.dist-info/METADATA
bizyui-1.2.94.dist-info/WHEEL
bizyui-1.2.94.dist-info/top_level.txt
bizyui-1.2.94.dist-info/RECORD
