Metadata-Version: 2.4
Name: bizyui
Version: 1.2.94
Summary: Web resources for [a/BizyAir](https://github.com/siliconflow/BizyAir) which contains Comfy Nodes that can run in any environment.
Author-email: SiliconFlow <yaochi@siliconflow.cn>
Project-URL: Repository, https://github.com/siliconflow/BizyAir
Classifier: Programming Language :: Python :: 3
Classifier: License :: OSI Approved :: MIT License
Classifier: Operating System :: OS Independent
Requires-Python: >=3.10
